neutrino/__init__.py
neutrino/conf/__init__.py
neutrino/kafka/__init__.py
neutrino/kafka/agent.py
neutrino/kafka/tools.py
neutrino/logging/__init__.py
neutrino/logging/handler.py
neutrino/mcp/__init__.py
neutrino/mcp/api_server.py
neutrino/mcp/application_server.py
neutrino/mcp/cli_client.py
neutrino/mcp/main.py
neutrino/mcp/mcp_env.py
neutrino/mcp/mcp_server.py
neutrino/mcp/prompt_template.py
neutrino/mcp/ui_client.py
neutrino/mcp/utils.py
neutrino/message/__init__.py
neutrino/onboard/__init__.py
neutrino/onboard/agent.py
neutrino/pipeline/__init__.py
neutrino/pipeline/agent.py
neutrino/pipeline/cdc.py
neutrino/pipeline/ddl_translation.py
neutrino/timeplus/__init__.py
neutrino/timeplus/analyzer.py
neutrino/timeplus/text2sql.py
neutrino/timeplus/utils.py
neutrino/utils/__init__.py
neutrino/utils/tools.py
timeplus_neutrino-0.1.15.dist-info/METADATA
timeplus_neutrino-0.1.15.dist-info/WHEEL
timeplus_neutrino-0.1.15.dist-info/top_level.txt
timeplus_neutrino-0.1.15.dist-info/RECORD
