Metadata-Version: 2.4
Name: timeplus-neutrino
Version: 0.1.15
Summary: Timeplus neutrino is a python library for Timeplus AI agent
Home-page: https://github.com/timeplus-io/neutrino
Author: Gang Tao
Author-email: gang@timeplus.io
Classifier: License :: OSI Approved :: Apache Software License
Classifier: Programming Language :: Python :: 3.9
Requires-Dist: urllib3>=1.15
Requires-Dist: six>=1.10
Requires-Dist: certifi
Requires-Dist: sseclient-py>=1.7.2
Requires-Dist: openai>=1.61.1
Requires-Dist: setuptools_scm>=6.0.0
Requires-Dist: proton_driver
Requires-Dist: confluent-kafka
Requires-Dist: autogen-core==0.6.1
Requires-Dist: autogen-ext==0.6.1
Requires-Dist: autogen-agentchat==0.6.1
Requires-Dist: cryptography
Requires-Dist: mcp>=1.3.0
Requires-Dist: mcp[cli]>=1.3.0
Requires-Dist: python-dotenv>=1.0.1
Requires-Dist: uvicorn>=0.34.0
Requires-Dist: timeplus-connect>=0.8.16
Requires-Dist: confluent-kafka
Requires-Dist: pip-system-certs>=4.0
Requires-Dist: anthropic>=0.49.0
Requires-Dist: fastapi
Requires-Dist: jinja2
Requires-Dist: websockets
Requires-Dist: fastapi-mcp==0.3.3
